modopt/__init__.py
modopt/base/__init__.py
modopt/base/backend.py
modopt/base/np_adjust.py
modopt/base/observable.py
modopt/base/transform.py
modopt/base/types.py
modopt/interface/__init__.py
modopt/interface/errors.py
modopt/interface/log.py
modopt/math/__init__.py
modopt/math/convolve.py
modopt/math/matrix.py
modopt/math/metrics.py
modopt/math/stats.py
modopt/opt/__init__.py
modopt/opt/cost.py
modopt/opt/gradient.py
modopt/opt/proximity.py
modopt/opt/reweight.py
modopt/opt/algorithms/__init__.py
modopt/opt/algorithms/admm.py
modopt/opt/algorithms/base.py
modopt/opt/algorithms/forward_backward.py
modopt/opt/algorithms/gradient_descent.py
modopt/opt/algorithms/primal_dual.py
modopt/opt/linear/__init__.py
modopt/opt/linear/base.py
modopt/opt/linear/wavelet.py
modopt/plot/__init__.py
modopt/plot/cost_plot.py
modopt/signal/__init__.py
modopt/signal/filter.py
modopt/signal/noise.py
modopt/signal/positivity.py
modopt/signal/svd.py
modopt/signal/validation.py
modopt/signal/wavelet.py
modopt-1.7.2.dist-info/LICENCE.txt
modopt-1.7.2.dist-info/METADATA
modopt-1.7.2.dist-info/WHEEL
modopt-1.7.2.dist-info/top_level.txt
modopt-1.7.2.dist-info/RECORD
