Metadata-Version: 2.1
Name: modopt
Version: 1.7.2
Summary: Modular Optimisation tools for soliving inverse problems.
Author-email: Samuel Farrens <samuel.farrens@cea.fr>, Chaithya GR <chaithyagr@gmail.com>, Pierre-Antoine Comby <pierre-antoine.comby@cea.fr>, Philippe Ciuciu <philippe.ciuciu@cea.fr>
License: MIT License
Requires-Python: >=3.8
License-File: LICENCE.txt
Requires-Dist: numpy
Requires-Dist: scipy
Requires-Dist: tqdm
Requires-Dist: importlib-metadata
Provides-Extra: dev
Requires-Dist: black ; extra == 'dev'
Requires-Dist: ruff ; extra == 'dev'
Provides-Extra: doc
Requires-Dist: myst-parser ; extra == 'doc'
Requires-Dist: nbsphinx ; extra == 'doc'
Requires-Dist: nbsphinx-link ; extra == 'doc'
Requires-Dist: sphinx-gallery ; extra == 'doc'
Requires-Dist: numpydoc ; extra == 'doc'
Requires-Dist: sphinxawesome-theme ; extra == 'doc'
Requires-Dist: sphinxcontrib-bibtex ; extra == 'doc'
Provides-Extra: gpu
Requires-Dist: torch ; extra == 'gpu'
Requires-Dist: ptwt ; extra == 'gpu'
Provides-Extra: test
Requires-Dist: pytest <8.0.0 ; extra == 'test'
Requires-Dist: pytest-cases ; extra == 'test'
Requires-Dist: pytest-cov ; extra == 'test'
Requires-Dist: pytest-xdist ; extra == 'test'
Requires-Dist: pytest-sugar ; extra == 'test'
